chat2edit/__init__.py
chat2edit/chat2edit.py
chat2edit/context/providers/__init__.py
chat2edit/context/providers/context_provider.py
chat2edit/context/providers/impl/calculator_context_provider.py
chat2edit/context/strategies/__init__.py
chat2edit/context/strategies/context_strategy.py
chat2edit/context/strategies/impl/default_context_strategy.py
chat2edit/context/utils/__init__.py
chat2edit/context/utils/assign_context_values.py
chat2edit/context/utils/path_to_value.py
chat2edit/context/utils/safe_deepcopy.py
chat2edit/context/utils/value_to_path.py
chat2edit/execution/decorators/__init__.py
chat2edit/execution/decorators/deepcopy_parameter.py
chat2edit/execution/decorators/feedback_empty_list_parameters.py
chat2edit/execution/decorators/feedback_ignored_return_value.py
chat2edit/execution/decorators/feedback_invalid_parameter_type.py
chat2edit/execution/decorators/feedback_mismatch_list_parameters.py
chat2edit/execution/decorators/feedback_missing_all_optional_parameters.py
chat2edit/execution/decorators/feedback_unexpected_error.py
chat2edit/execution/decorators/respond.py
chat2edit/execution/exceptions/__init__.py
chat2edit/execution/exceptions/feedback_exception.py
chat2edit/execution/exceptions/response_exception.py
chat2edit/execution/signaling/__init__.py
chat2edit/execution/signaling/signal_manager.py
chat2edit/execution/strategies/__init__.py
chat2edit/execution/strategies/execution_strategy.py
chat2edit/execution/strategies/impl/default_execution_strategy.py
chat2edit/execution/utils/__init__.py
chat2edit/execution/utils/async_call_corrector.py
chat2edit/models/__init__.py
chat2edit/models/chat_cycle.py
chat2edit/models/error.py
chat2edit/models/execution_block.py
chat2edit/models/execution_error.py
chat2edit/models/exemplar.py
chat2edit/models/exemplary_chat_cycle.py
chat2edit/models/exemplary_execution_block.py
chat2edit/models/exemplary_prompt_cycle.py
chat2edit/models/exemplary_prompt_exchange.py
chat2edit/models/feedback.py
chat2edit-4.1.7.dist-info/METADATA
chat2edit-4.1.7.dist-info/WHEEL
chat2edit-4.1.7.dist-info/licenses/LICENSE
chat2edit-4.1.7.dist-info/RECORD
