Metadata-Version: 2.4
Name: chat2edit
Version: 4.1.7
Summary: A small example package
License: CC BY-NC 4.0
License-File: LICENSE
Author: Le Tin Nghia
Author-email: nghialt3670@gmail.com
Requires-Python: >=3.10
Classifier: License :: Other/Proprietary License
Classifier: Operating System :: OS Independent
Classifier: Programming Language :: Python :: 3
Classifier: Programming Language :: Python :: 3.10
Classifier: Programming Language :: Python :: 3.11
Classifier: Programming Language :: Python :: 3.12
Classifier: Programming Language :: Python :: 3.13
Classifier: Programming Language :: Python :: 3.14
Requires-Dist: IPython (==8.29.0)
Requires-Dist: PyYAML (==6.0.2)
Requires-Dist: astor (==0.8.1)
Requires-Dist: black (==24.10.0)
Requires-Dist: google-generativeai (==0.8.3)
Requires-Dist: openai (==0.28.0)
Project-URL: Homepage, https://github.com/nghialt3670/chat2edit-python
Project-URL: Issues, https://github.com/nghialt3670/chat2edit-python/issues
